simphyni/Snakefile.py
simphyni/__init__.py
simphyni/simphyni_cli.py
simphyni/Simulation/Utils.py
simphyni/Simulation/__init__.py
simphyni/Simulation/pair_statistics.py
simphyni/Simulation/simulation.py
simphyni/Simulation/tree_simulator.py
simphyni/envs/simphyni.yaml
simphyni/scripts/GL_tab.py
simphyni/scripts/countgainloss_tab.py
simphyni/scripts/pastml.py
simphyni/scripts/reformat_csv.py
simphyni/scripts/reformat_tree.py
simphyni/scripts/runSimPhyNI.py
simphyni-1.0.2.dist-info/licenses/LICENSE
simphyni-1.0.2.dist-info/METADATA
simphyni-1.0.2.dist-info/WHEEL
simphyni-1.0.2.dist-info/entry_points.txt
simphyni-1.0.2.dist-info/top_level.txt
simphyni-1.0.2.dist-info/RECORD
