Metadata-Version: 2.4
Name: simphyni
Version: 1.0.2
Summary: SimPhyni: a tool for phylogenetic trait simulation and inference.
Author-email: Ishaq Balogun <ishaqobalogun@gmail.com>
License: MIT
Requires-Python: <3.13,>=3.11
License-File: LICENSE
Requires-Dist: ete3>=3.1.3
Requires-Dist: joblib>=1.4.2
Requires-Dist: matplotlib>=3.10.1
Requires-Dist: numpy>=2.2.3
Requires-Dist: numba>=0.62.0
Requires-Dist: pandas>=2.2.3
Requires-Dist: scikit-learn>=1.6.1
Requires-Dist: seaborn<0.14,>=0.13.0
Requires-Dist: setuptools>=75.8.0
Requires-Dist: statsmodels>=0.14.4
Requires-Dist: wheel>=0.45.1
Requires-Dist: annotated-types>=0.7.0
Requires-Dist: biopython>=1.85
Requires-Dist: certifi>=2025.1.31
Requires-Dist: charset-normalizer>=3.4.1
Requires-Dist: idna>=3.10
Requires-Dist: itolapi>=4.1.5
Requires-Dist: jinja2>=3.1.6
Requires-Dist: markupsafe>=3.0.2
Requires-Dist: pastml>=1.9.50
Requires-Dist: pydantic>=2.10.6
Requires-Dist: pydantic-core>=2.27.2
Requires-Dist: requests>=2.32.3
Requires-Dist: scipy>=1.14.0
Requires-Dist: urllib3>=2.4.0
Requires-Dist: snakemake>=9.10
Dynamic: license-file
